repo_structure_generator/__init__.py
repo_structure_generator/generator.py
repo_structure_generator-1.3.0.dist-info/LICENSE
repo_structure_generator-1.3.0.dist-info/METADATA
repo_structure_generator-1.3.0.dist-info/WHEEL
repo_structure_generator-1.3.0.dist-info/entry_points.txt
repo_structure_generator-1.3.0.dist-info/top_level.txt
repo_structure_generator-1.3.0.dist-info/RECORD
