Metadata-Version: 2.1
Name: repo-structure-generator
Version: 1.3.0
Summary: A tool for generating structured documentation of software repository directory structures.
Home-page: https://github.com/aceamarco/repo-structure-generator
Author: Marco Acea
Author-email: aceamarco@gmail.com
License: MIT
License-File: LICENSE
